tableconverter/__init__.py
tableconverter/__main__.py
tableconverter/main.py
tableconverter/converter/__init__.py
tableconverter/converter/backend.py
tableconverter/converter/frontend.py
tableconverter/converter/transpiler.py
tableconverter/model/__init__.py
tableconverter/model/table.py
tableconverter/util/__init__.py
tableconverter/util/html_entity.json
tableconverter/util/html_entity.py
tableconverter-0.1.4.dist-info/AUTHORS.md
tableconverter-0.1.4.dist-info/LICENSE
tableconverter-0.1.4.dist-info/METADATA
tableconverter-0.1.4.dist-info/WHEEL
tableconverter-0.1.4.dist-info/entry_points.txt
tableconverter-0.1.4.dist-info/top_level.txt
tableconverter-0.1.4.dist-info/RECORD
